vectra/__init__.py
vectra/berendsen.py
vectra/decompose.py
vectra/math.py
vectra-0.1.2.dist-info/METADATA
vectra-0.1.2.dist-info/WHEEL
vectra-0.1.2.dist-info/licenses/LICENSE
vectra-0.1.2.dist-info/RECORD
