Metadata-Version: 2.4
Name: vectra
Version: 0.1.2
Summary: Vector Transformations and Thermostats for ASE Atoms and Molecules
Project-URL: Repository, https://github.com/zincware/vectra
Project-URL: Releases, https://github.com/zincware/vectra/releases
Project-URL: Discord, https://discord.gg/7ncfwhsnm4
Author-email: Fabian Zills <fzills@icp.uni-stuttgart.de>
License-Expression: MIT
License-File: LICENSE
Requires-Python: >=3.11
Requires-Dist: ase>=3.25.0
Requires-Dist: numpy>=1.19.5
Requires-Dist: rdkit2ase>=0.1.9
